pynonthermal/__init__.py
pynonthermal/axelrod.py
pynonthermal/base.py
pynonthermal/collion.py
pynonthermal/constants.py
pynonthermal/excitation.py
pynonthermal/spencerfano.py
pynonthermal/data/binding_energies_lotz_tab1and2.txt
pynonthermal/data/collion-AR1985.txt
pynonthermal/data/collion-reference.txt
pynonthermal/data/collion.txt
pynonthermal/data/electron_shell_occupancy.txt
pynonthermal/data/nist_ionization.txt.zst
pynonthermal/data/artis_files/adata.txt
pynonthermal/data/artis_files/compositiondata.txt
pynonthermal/data/artis_files/transitiondata.txt.zst
pynonthermal/data/artis_files/atomic_data_logs/fe1.txt
pynonthermal/data/artis_files/atomic_data_logs/fe2.txt
pynonthermal/data/artis_files/atomic_data_logs/fe3.txt
pynonthermal/data/artis_files/atomic_data_logs/fe4.txt
pynonthermal/data/artis_files/atomic_data_logs/fe5.txt
pynonthermal/data/artis_files/atomic_data_logs/he1.txt
pynonthermal/data/artis_files/atomic_data_logs/he2.txt
pynonthermal/data/artis_files/atomic_data_logs/o1.txt
pynonthermal/data/artis_files/atomic_data_logs/o2.txt
pynonthermal/data/artis_files/atomic_data_logs/o3.txt
pynonthermal/data/artis_files/atomic_data_logs/o4.txt
pynonthermal/tests/__init__.py
pynonthermal/tests/test_sfsolve.py
pynonthermal/tests/output/.gitignore
pynonthermal-2025.3031.2.dist-info/licenses/LICENSE
pynonthermal-2025.3031.2.dist-info/METADATA
pynonthermal-2025.3031.2.dist-info/WHEEL
pynonthermal-2025.3031.2.dist-info/top_level.txt
pynonthermal-2025.3031.2.dist-info/RECORD
