Metadata-Version: 2.4
Name: pynonthermal
Version: 2025.3031.2
Summary: A non-thermal electron deposition (Spencer-Fano equation) solver.
Author-email: "Luke J. Shingles" <luke.shingles@gmail.com>
License: MIT License
Project-URL: Repository, https://www.github.com/lukeshingles/pynonthermal/
Classifier: License :: OSI Approved :: MIT License
Classifier: Programming Language :: Python :: 3.11
Classifier: Programming Language :: Python :: 3.12
Classifier: Programming Language :: Python :: 3.13
Classifier: Intended Audience :: Science/Research
Requires-Python: >=3.11
License-File: LICENSE
Requires-Dist: artistools>=2024.07.04.2
Requires-Dist: matplotlib>=3.9.1
Requires-Dist: numpy>=1.19.4
Requires-Dist: polars>=1.20.0
Requires-Dist: scipy>=1.5.4
Dynamic: license-file
